{ "chiefBonus": {}, "coming": [], "movieIds": [1262080, 1278598, 1225503, 1302235, 1198179, 1302134, 718, 1213261, 1355429, 1355662], "stid": "576591972453269000", "stids": [{ "movieId": 1262080, "stid": "576591972453269000_a1262080_c0" }, { "movieId": 1278598, "stid": "576591972453269000_a1278598_c1" }, { "movieId": 1225503, "stid": "576591972453269000_a1225503_c2" }, { "movieId": 1302235, "stid": "576591972453269000_a1302235_c3" }, { "movieId": 1198179, "stid": "576591972453269000_a1198179_c4" }, { "movieId": 1302134, "stid": "576591972453269000_a1302134_c5" }, { "movieId": 718, "stid": "576591972453269000_a718_c6" }, { "movieId": 1213261, "stid": "576591972453269000_a1213261_c7" }, { "movieId": 1355429, "stid": "576591972453269000_a1355429_c8" }, { "movieId": 1355662, "stid": "576591972453269000_a1355662_c9" }], "total": 10, "movieList": [{ "id": 1262080, "haspromotionTag": false, "img": "http://p0.meituan.net/w.h/movie/db95f0ad6a6963f3c9b21a8e53cdcad72771847.jpg", "version": "", "nm": "摇摆神探", "preShow": false, "sc": 0, "globalReleased": false, "wish": 1998, "star": "邵彤,四喜,季骜杰", "rt": "2021-07-17", "showInfo": "2021-07-17上映", "showst": 4, "wishst": 0 }, { "id": 1278598, "haspromotionTag": false, "img": "http://p0.meituan.net/w.h/movie/cc08f286aea37c3355fb4bb2441aef3f3457731.jpg", "version": "", "nm": "你好世界", "preShow": false, "sc": 9.1, "globalReleased": true, "wish": 199467, "star": "北村匠海,松坂桃李,滨边美波", "rt": "2021-06-11", "showInfo": "今天1家影院放映7场", "showst": 3, "wishst": 0 }, { "id": 1225503, "haspromotionTag": false, "img": "http://p0.meituan.net/w.h/movie/49b453507a60d99a9b9d42755950029994987.jpg", "version": "", "nm": "比得兔2：逃跑计划", "preShow": false, "sc": 9.2, "globalReleased": true, "wish": 53317, "star": "郭麒麟,詹姆斯·柯登,萝丝·拜恩", "rt": "2021-06-11", "showInfo": "今天1家影院放映7场", "showst": 3, "wishst": 0 }, { "id": 1302235, "haspromotionTag": false, "img": "http://p0.meituan.net/w.h/movie/487652d6aa8794be39aa956fd77233551990319.jpg", "version": "", "nm": "超越", "preShow": false, "sc": 8.4, "globalReleased": true, "wish": 237013, "star": "郑恺,李昀锐,曹炳琨", "rt": "2021-06-12", "showInfo": "今天1家影院放映7场", "showst": 3, "wishst": 0 }, { "id": 1198179, "haspromotionTag": false, "img": "http://p1.meituan.net/w.h/movie/6a0b995daf79a1112aab8fb441f655ff3419929.jpg", "version": "", "nm": "阳光姐妹淘", "preShow": false, "sc": 8.9, "globalReleased": true, "wish": 177876, "star": "殷桃,曾黎,张歆艺", "rt": "2021-06-11", "showInfo": "今天1家影院放映6场", "showst": 3, "wishst": 0 }, { "id": 1302134, "haspromotionTag": false, "img": "http://p0.meituan.net/w.h/movie/69291d617c3dc5dcac5e3bf29dda63ac2200192.jpg", "version": "v3d", "nm": "哆啦A梦：伴我同行2", "preShow": false, "sc": 9, "globalReleased": true, "wish": 271443, "star": "水田山葵,大原惠美,嘉数由美", "rt": "2021-05-28", "showInfo": "今天1家影院放映6场", "showst": 3, "wishst": 0 }, { "id": 718, "haspromotionTag": false, "img": "http://p1.meituan.net/w.h/movie/b5adcadc67ea24afadc66739bdc9abb33432367.jpg", "version": "", "nm": "天堂电影院", "preShow": false, "sc": 9.4, "globalReleased": true, "wish": 22703, "star": "菲利浦·诺瓦雷,雅克·贝汉,马克·莱昂纳蒂", "rt": "2021-06-11", "showInfo": "今天1家影院放映6场", "showst": 3, "wishst": 0 }, { "id": 1213261, "haspromotionTag": false, "img": "http://p0.meituan.net/w.h/movie/32ec8754ef53c9239ebae0af62b8581a393364.jpg", "version": "v2d imax", "nm": "热带往事", "preShow": false, "sc": 7.4, "globalReleased": true, "wish": 65195, "star": "彭于晏,张艾嘉,王砚辉", "rt": "2021-06-12", "showInfo": "今天1家影院放映6场", "showst": 3, "wishst": 0 }, { "id": 1355429, "haspromotionTag": false, "img": "http://p0.meituan.net/w.h/movie/dac596f995e8dd0252664722c1c0e1b72007737.jpg", "version": "v3d", "nm": "疯狂丑小鸭2靠谱英雄", "preShow": false, "sc": 0, "globalReleased": true, "wish": 14062, "star": "苏旖旎,王雪沁,许子尧", "rt": "2021-06-12", "showInfo": "今天1家影院放映2场", "showst": 3, "wishst": 0 }, { "id": 1355662, "haspromotionTag": false, "img": "http://p0.meituan.net/w.h/movie/a4cb98a5e79cbe8f458c1c3b869355d12513292.jpg", "version": "", "nm": "饮料超人", "preShow": false, "sc": 0, "globalReleased": true, "wish": 11782, "star": "郝翔海,陈喆,林强", "rt": "2021-06-12", "showInfo": "今天1家影院放映2场", "showst": 3, "wishst": 0 }] }